erebusfall/__init__.py
erebusfall/core.py
erebusfall/benthic_stacks/__init__.py
erebusfall/benthic_stacks/lr04.csv
erebusfall/tests/__init__.py
erebusfall/tests/test_core.py
erebusfall-0.0.3.dist-info/LICENSE
erebusfall-0.0.3.dist-info/METADATA
erebusfall-0.0.3.dist-info/WHEEL
erebusfall-0.0.3.dist-info/top_level.txt
erebusfall-0.0.3.dist-info/RECORD
