Metadata-Version: 2.1
Name: erebusfall
Version: 0.0.3
Summary: Apply a simple ice-volume correction to marine-isotope proxy records in Python
Home-page: https://github.com/brews/erebusfall
Author: S. Brewster Malevich
Author-email: malevich@email.arizona.edu
License: GPLv3
Keywords: marine isotope paleoclimate proxy deuterium d18o
Platform: UNKNOWN
Classifier: Development Status :: 5 - Production/Stable
Classifier: Intended Audience :: Developers
Classifier: Intended Audience :: Science/Research
Classifier: Topic :: Scientific/Engineering
Classifier: Topic :: Software Development
Classifier: License :: OSI Approved :: GNU General Public License v3 or later (GPLv3+)
Classifier: Programming Language :: Python :: 3
Requires-Dist: numpy
Requires-Dist: scipy
